bng_data/__init__.py
bng_data/elastic_client.py
bng_data/elastic_client5.py
bng_data/es_query_builder.py
bng_data/http_client.py
bng_data-0.1.5.dist-info/LICENSE.txt
bng_data-0.1.5.dist-info/METADATA
bng_data-0.1.5.dist-info/WHEEL
bng_data-0.1.5.dist-info/RECORD
