Metadata-Version: 2.1
Name: bng-data
Version: 0.1.5
Summary: 
Author: Brian Mitchell
Author-email: bmitchell@beeldengeluid.nl
Requires-Python: >=3.9,<4.0
Classifier: Programming Language :: Python :: 3
Classifier: Programming Language :: Python :: 3.9
Classifier: Programming Language :: Python :: 3.10
Classifier: Programming Language :: Python :: 3.11
Requires-Dist: elasticsearch (>=8.6.2,<9.0.0)
Requires-Dist: elasticsearch5 (>=5.5.6,<6.0.0)
Requires-Dist: requests (>=2.28.2,<3.0.0)
